AUTHORS.rst
CONTRIBUTING.rst
HISTORY.rst
LICENSE
MANIFEST.in
README.rst
setup.cfg
setup.py
docs/Makefile
docs/authors.rst
docs/conf.py
docs/contributing.rst
docs/history.rst
docs/index.rst
docs/installation.rst
docs/make.bat
docs/readme.rst
docs/usage.rst
geospots/__init__.py
geospots/cli.py
geospots/geospots.py
geospots/openrouteservice.py
geospots/postgis.py
geospots/sector_maps.py
geospots.egg-info/PKG-INFO
geospots.egg-info/SOURCES.txt
geospots.egg-info/dependency_links.txt
geospots.egg-info/entry_points.txt
geospots.egg-info/not-zip-safe
geospots.egg-info/requires.txt
geospots.egg-info/top_level.txt
tests/__init__.py
tests/test_geospots.py