Metadata-Version: 1.2
Name: geospots
Version: 0.1.5
Summary: Geospots contains functions for dealing with spatial data
Home-page: https://bitbucket.org/indiciumtech/indicium_geospots
Author: Pedro Portela
Author-email: pedro.portela@indicium.tech
License: MIT license
Keywords: geospots
Platform: UNKNOWN
Classifier: Development Status :: 2 - Pre-Alpha
Classifier: Intended Audience :: Developers
Classifier: License :: OSI Approved :: MIT License
Classifier: Natural Language :: English
Classifier: Programming Language :: Python :: 3
Classifier: Programming Language :: Python :: 3.5
Classifier: Programming Language :: Python :: 3.6
Classifier: Programming Language :: Python :: 3.7
Classifier: Programming Language :: Python :: 3.8
Requires-Python: >=3.5
